bangla/__init__.py
bangla-0.0.4.dist-info/licenses/LICENSE
bangla-0.0.4.dist-info/METADATA
bangla-0.0.4.dist-info/WHEEL
bangla-0.0.4.dist-info/top_level.txt
bangla-0.0.4.dist-info/RECORD
